xgboost_distribution/__init__.py
xgboost_distribution/compat.py
xgboost_distribution/metrics.py
xgboost_distribution/model.py
xgboost_distribution/utils.py
xgboost_distribution/distributions/__init__.py
xgboost_distribution/distributions/base.py
xgboost_distribution/distributions/exponential.py
xgboost_distribution/distributions/laplace.py
xgboost_distribution/distributions/log_normal.py
xgboost_distribution/distributions/negative_binomial.py
xgboost_distribution/distributions/normal.py
xgboost_distribution/distributions/poisson.py
xgboost_distribution/distributions/utils.py
xgboost_distribution-0.4.0.dist-info/licenses/AUTHORS.rst
xgboost_distribution-0.4.0.dist-info/licenses/LICENSE.txt
xgboost_distribution-0.4.0.dist-info/METADATA
xgboost_distribution-0.4.0.dist-info/WHEEL
xgboost_distribution-0.4.0.dist-info/top_level.txt
xgboost_distribution-0.4.0.dist-info/RECORD
