Metadata-Version: 2.4
Name: xgboost-distribution
Version: 0.4.0
Summary: XGBoost for probabilistic prediction.
Home-page: https://github.com/CDonnerer/xgboost-distribution/
Author: Christian Donnerer
Author-email: christian.donnerer@gmail.com
License: MIT
Project-URL: Documentation, https://xgboost-distribution.readthedocs.io/en/latest/?badge=latest
Platform: any
Classifier: Development Status :: 4 - Beta
Classifier: Programming Language :: Python
Requires-Python: >=3.10
License-File: LICENSE.txt
License-File: AUTHORS.rst
Requires-Dist: scikit-learn
Requires-Dist: xgboost-cpu>=3.0.0; platform_machine == "x86_64" and (platform_system == "Windows" or platform_system == "Linux")
Requires-Dist: xgboost>=3.0.0; platform_machine != "x86_64" or (platform_system != "Windows" and platform_system != "Linux")
Provides-Extra: testing
Requires-Dist: setuptools; extra == "testing"
Requires-Dist: pandas; extra == "testing"
Requires-Dist: pytest; extra == "testing"
Requires-Dist: pytest-cov; extra == "testing"
Provides-Extra: gpu
Requires-Dist: xgboost>=3.0.0; extra == "gpu"
Dynamic: license-file
